MANIFEST.in
requirements.txt
setup.cfg
setup.py
zembed/__init__.py
zembed/api.py
zembed/exceptions.py
zembed.egg-info/PKG-INFO
zembed.egg-info/SOURCES.txt
zembed.egg-info/dependency_links.txt
zembed.egg-info/requires.txt
zembed.egg-info/top_level.txt